pandasreporter/__init__.py
pandasreporter/formatters/__init__.py
pandasreporter/formatters/html.py
pandasreporter/formatters/json.py
pandasreporter/formatters/text.py
pandasreporter/formatters/yaml_.py
pandasreporter-1.0.0.dist-info/METADATA
pandasreporter-1.0.0.dist-info/WHEEL
pandasreporter-1.0.0.dist-info/licenses/LICENSE
pandasreporter-1.0.0.dist-info/RECORD
