Metadata-Version: 2.4
Name: pandasreporter
Version: 1.0.0
Summary: Report builder for Pandas DataFrame
License: Apache-2.0
License-File: LICENSE
Keywords: pandasreporter,...
Author: Cliffano Subagio
Author-email: cliffano@gmail.com
Requires-Python: >=3.10,<4.0
Classifier: License :: OSI Approved :: Apache Software License
Classifier: Operating System :: OS Independent
Classifier: Programming Language :: Python :: 3
Classifier: Programming Language :: Python :: 3.10
Classifier: Programming Language :: Python :: 3.11
Classifier: Programming Language :: Python :: 3.12
Classifier: Programming Language :: Python :: 3.13
Classifier: Programming Language :: Python :: 3.14
Requires-Dist: PyYAML (>=6.0.3,<6.1.0)
Requires-Dist: dominate (>=2.9.1,<2.10.0)
Requires-Dist: tabulate (>=0.9.0,<0.10.0)
Project-URL: Documentation, https://github.com/cliffano/pandas-reporter
Project-URL: Homepage, https://github.com/cliffano/pandas-reporter
Project-URL: Repository, https://github.com/cliffano/pandas-reporter
